wyoming_azure_speech/__init__.py
wyoming_azure_speech/__main__.py
wyoming_azure_speech/handler.py
wyoming_azure_speech/speech_service.py
wyoming_azure_speech/synthesizer.py
wyoming_azure_speech/transcriber.py
wyoming_azure_speech-0.1.1.dist-info/LICENSE
wyoming_azure_speech-0.1.1.dist-info/METADATA
wyoming_azure_speech-0.1.1.dist-info/WHEEL
wyoming_azure_speech-0.1.1.dist-info/entry_points.txt
wyoming_azure_speech-0.1.1.dist-info/top_level.txt
wyoming_azure_speech-0.1.1.dist-info/RECORD
