Metadata-Version: 2.1
Name: wyoming-azure-speech
Version: 0.1.1
Summary: Wyoming Server for Azure AI Speech
Home-page: https://github.com/shmuelzon/wyoming-azure-speech
Download-URL: https://github.com/shmuelzon/wyoming-azure-speech/tarball/0.1.1
Author: Shmuelzon
License: MIT
Requires-Python: >=3.9
License-File: LICENSE
Requires-Dist: azure-cognitiveservices-speech==1.41.1
Requires-Dist: requests
Requires-Dist: wyoming==1.6.0
Provides-Extra: test
Requires-Dist: build; extra == "test"
Requires-Dist: ruff; extra == "test"
Requires-Dist: setuptools; extra == "test"
